thredds
