Metadata-Version: 1.0
Name: thredds
Version: 0.1.3
Summary: THREDDS catalog generator.
Home-page: http://pydap.org/related/thredds.html
Author: Roberto De Almeida
Author-email: rob@pydap.org
License: MIT
Download-URL: http://cheeseshop.python.org/packages/source/t/thredds/thredds-0.1.3.tar.gz
Keywords: thredds data
Platform: UNKNOWN
Classifier: Development Status :: 4 - Beta
Classifier: Environment :: Console
Classifier: Intended Audience :: Developers
Classifier: Intended Audience :: Science/Research
Classifier: License :: OSI Approved :: MIT License
Classifier: Operating System :: OS Independent
Classifier: Programming Language :: Python
Classifier: Topic :: Scientific/Engineering
Classifier: Topic :: Software Development :: Libraries :: Python Modules
